{"zoom": 7, "x": 122, "y": 47, "points": [{"lat": 41.4142, "lng": 164.9032, "id": "344104", "name": "Phoebastria immutabilis", "sprite": "sp-anchoviella_juruasanga.png", "group": "other", "rarity": 1}, {"lat": 41.25, "lng": 165.0, "id": "103408", "name": "Oikopleura (Coecaria) fusiformis", "sprite": "sp-anchoviella_juruasanga.png", "group": "other", "rarity": 1}, {"lat": 41.25, "lng": 165.0, "id": "103414", "name": "Oikopleura (Coecaria) longicauda", "sprite": "sp-anchoviella_juruasanga.png", "group": "other", "rarity": 1}, {"lat": 41.39, "lng": 164.6187, "id": "2", "name": "Animalia", "sprite": "sp-anchoviella_juruasanga.png", "group": "other", "rarity": 1}, {"lat": 41.86, "lng": 164.438, "id": "137202", "name": "Puffinus griseus", "sprite": "sp-anchoviella_juruasanga.png", "group": "other", "rarity": 1}, {"lat": 41.34, "lng": 165.0, "id": "148898", "name": "Bacillariophyta", "sprite": "sp-anchoviella_juruasanga.png", "group": "other", "rarity": 1}, {"lat": 41.5559, "lng": 165.0074, "id": "148899", "name": "Bacillariophyceae", "sprite": "sp-anchoviella_juruasanga.png", "group": "other", "rarity": 1}, {"lat": 41.5, "lng": 165.0, "id": "344106", "name": "Phoebastria nigripes", "sprite": "sp-anchoviella_juruasanga.png", "group": "other", "rarity": 1}, {"lat": 41.3394, "lng": 165.0, "id": "5949", "name": "Sagittoidea", "sprite": "sp-anchoviella_juruasanga.png", "group": "other", "rarity": 1}, {"lat": 42.25, "lng": 165.0, "id": "103413", "name": "Oikopleura (Vexillaria) labradoriensis", "sprite": "sp-anchoviella_juruasanga.png", "group": "other", "rarity": 1}, {"lat": 42.0, "lng": 165.0, "id": "103370", "name": "Appendicularia sicula", "sprite": "sp-anchoviella_juruasanga.png", "group": "other", "rarity": 1}, {"lat": 41.0, "lng": 165.0, "id": "103367", "name": "Oikopleura", "sprite": "sp-anchoviella_juruasanga.png", "group": "other", "rarity": 1}, {"lat": 42.0306, "lng": 164.6522, "id": "137205", "name": "Caretta caretta", "sprite": "sp-green_sea_turtle.png", "group": "sea_turtle", "rarity": 1}, {"lat": 41.0, "lng": 165.0, "id": "103364", "name": "Megalocercus", "sprite": "sp-anchoviella_juruasanga.png", "group": "other", "rarity": 1}, {"lat": 41.0, "lng": 165.0, "id": "103386", "name": "Fritillaria pellucida", "sprite": "sp-anchoviella_juruasanga.png", "group": "other", "rarity": 1}]}