{"zoom": 7, "x": 31, "y": 52, "points": [{"lat": 31.0148, "lng": -90.9586, "id": "270054", "name": "Notropis", "sprite": "sp-enteromius.png", "group": "carp_minnow", "rarity": 1}, {"lat": 30.2539, "lng": -90.7372, "id": "159227", "name": "Inland silverside", "thumb": "tn_Meber_u0.jpg", "sprite": "sp-anchoviella_juruasanga.png", "group": "other", "rarity": 1, "waterType": "Brackish"}, {"lat": 30.6764, "lng": -91.3908, "id": "156996", "name": "Spisula solidissima", "sprite": "sp-blue_mussel.png", "group": "clam_mussel", "rarity": 1}, {"lat": 30.6764, "lng": -91.3908, "id": "506524", "name": "Orthoyoldia solenoides", "sprite": "sp-blue_mussel.png", "group": "clam_mussel", "rarity": 1}, {"lat": 31.9375, "lng": -92.029, "id": "458583", "name": "Xylophaga multichela", "sprite": "sp-blue_mussel.png", "group": "clam_mussel", "rarity": 1}, {"lat": 30.0408, "lng": -90.5364, "id": "159483", "name": "Atlantic bumper", "thumb": "tn_Chchr_ug.jpg", "sprite": "sp-anchoviella_juruasanga.png", "group": "other", "rarity": 1, "waterType": "Brackish"}, {"lat": 30.6764, "lng": -91.3908, "id": "156859", "name": "Geukensia demissa", "sprite": "sp-blue_mussel.png", "group": "clam_mussel", "rarity": 1}, {"lat": 30.3427, "lng": -91.2401, "id": "158707", "name": "White sucker", "thumb": "tn_Cacom_u7.jpg", "sprite": "sp-anchoviella_juruasanga.png", "group": "other", "rarity": 1, "waterType": "Brackish"}, {"lat": 29.7356, "lng": -92.7372, "id": "137669", "name": "Anadara", "sprite": "sp-blue_mussel.png", "group": "clam_mussel", "rarity": 1}, {"lat": 29.7356, "lng": -92.7372, "id": "419996", "name": "Costoanachis semiplicata", "sprite": "sp-cowrie_shell.png", "group": "sea_snail", "rarity": 1}, {"lat": 30.0074, "lng": -90.5312, "id": "159249", "name": "Pinfish", "thumb": "tn_Larho_u1.jpg", "sprite": "sp-anchoviella_juruasanga.png", "group": "other", "rarity": 1, "waterType": "Brackish"}, {"lat": 30.3117, "lng": -90.9862, "id": "159309", "name": "Lucania", "sprite": "sp-anchoviella_juruasanga.png", "group": "other", "rarity": 1}, {"lat": 30.0306, "lng": -90.4931, "id": "159310", "name": "Rainwater killifish", "thumb": "tn_Lupar_m2.jpg", "sprite": "sp-anchoviella_juruasanga.png", "group": "other", "rarity": 1, "waterType": "Brackish"}, {"lat": 29.9227, "lng": -90.3193, "id": "127185", "name": "Rainbow trout", "thumb": "tn_Onmyk_f0.jpg", "sprite": "sp-atlantic_salmon.png", "group": "salmon_trout", "rarity": 1, "waterType": "Brackish"}, {"lat": 30.4551, "lng": -91.2569, "id": "126983", "name": "Flathead grey mullet", "thumb": "tn_Mucep_u4.jpg", "sprite": "sp-anchoviella_juruasanga.png", "group": "other", "rarity": 1, "waterType": "Brackish"}, {"lat": 31.7394, "lng": -90.525, "id": "151300", "name": "Percidae", "sprite": "sp-dicentrarchus.png", "group": "bass", "rarity": 1}, {"lat": 30.0, "lng": -90.05, "id": "159647", "name": "Atlantic moonfish", "thumb": "tn_Seset_u0.jpg", "sprite": "sp-anchoviella_juruasanga.png", "group": "other", "rarity": 1, "waterType": "Brackish"}, {"lat": 29.631, "lng": -92.029, "id": "106122", "name": "Balanus", "sprite": "sp-anchoviella_juruasanga.png", "group": "other", "rarity": 1}, {"lat": 30.0, "lng": -90.05, "id": "159126", "name": "Charadrius semipalmatus", "sprite": "sp-anchoviella_juruasanga.png", "group": "other", "rarity": 1}, {"lat": 29.5667, "lng": -91.9667, "id": "127309", "name": "Half-naked hatchetfish", "thumb": "tn_Arhem_u6.jpg", "sprite": "sp-anchoviella_juruasanga.png", "group": "other", "rarity": 1, "waterType": "Saltwater"}, {"lat": 29.8853, "lng": -91.2144, "id": "118100", "name": "Chironomidae", "sprite": "sp-anchoviella_juruasanga.png", "group": "other", "rarity": 1}, {"lat": 30.7131, "lng": -91.6839, "id": "157871", "name": "Lepisosteus", "sprite": "sp-anchoviella_juruasanga.png", "group": "other", "rarity": 1}, {"lat": 29.9444, "lng": -90.6429, "id": "181574", "name": "Cryptochironomus", "sprite": "sp-anchoviella_juruasanga.png", "group": "other", "rarity": 1}, {"lat": 30.4667, "lng": -90.0667, "id": "126971", "name": "Pearly razorfish", "thumb": "tn_Xynov_u0.jpg", "sprite": "sp-cleaner_wrasse.png", "group": "wrasse", "rarity": 1, "waterType": "Saltwater"}, {"lat": 29.7333, "lng": -90.9667, "id": "275444", "name": "Freckled pike-conger", "thumb": "tn_Homac_u2.jpg", "sprite": "sp-electric_eel.png", "group": "eel", "rarity": 1, "waterType": "Saltwater"}, {"lat": 29.9865, "lng": -91.092, "id": "878522", "name": "Ameritella texana", "sprite": "sp-blue_mussel.png", "group": "clam_mussel", "rarity": 1}, {"lat": 29.598, "lng": -91.424, "id": "489101", "name": "Sphaeriidae", "sprite": "sp-blue_mussel.png", "group": "clam_mussel", "rarity": 1}, {"lat": 30.6196, "lng": -91.559, "id": "276134", "name": "Eastern mosquitofish", "thumb": "tn_Gahol_f0.jpg", "sprite": "sp-anchoviella_juruasanga.png", "group": "other", "rarity": 1, "waterType": "Brackish"}, {"lat": 29.7356, "lng": -92.7372, "id": "138274", "name": "Olivella", "sprite": "sp-cowrie_shell.png", "group": "sea_snail", "rarity": 1}, {"lat": 30.0596, "lng": -90.832, "id": "156991", "name": "Rangia cuneata", "sprite": "sp-blue_mussel.png", "group": "clam_mussel", "rarity": 1}, {"lat": 30.6764, "lng": -91.3908, "id": "420776", "name": "Pododesmus rudis", "sprite": "sp-blue_mussel.png", "group": "clam_mussel", "rarity": 1}, {"lat": 31.204, "lng": -92.3255, "id": "154314", "name": "Grass carp", "thumb": "tn_Ctide_u4.jpg", "sprite": "sp-enteromius.png", "group": "carp_minnow", "rarity": 1, "waterType": "Brackish"}, {"lat": 30.6764, "lng": -91.3908, "id": "877061", "name": "Phrontis vibex", "sprite": "sp-cowrie_shell.png", "group": "sea_snail", "rarity": 1}, {"lat": 31.3347, "lng": -92.4778, "id": "298293", "name": "Carpio carpio", "sprite": "sp-enteromius.png", "group": "carp_minnow", "rarity": 1}, {"lat": 30.6764, "lng": -91.3908, "id": "464261", "name": "Radiolucina amianta", "sprite": "sp-blue_mussel.png", "group": "clam_mussel", "rarity": 1}, {"lat": 29.767, "lng": -91.915, "id": "1360", "name": "Actiniaria", "sprite": "sp-actiniidae.png", "group": "coral", "rarity": 1}, {"lat": 30.0, "lng": -90.05, "id": "159313", "name": "Squeteague", "thumb": "tn_Cyreg_u0.jpg", "sprite": "sp-anchoviella_juruasanga.png", "group": "other", "rarity": 1, "waterType": "Brackish"}, {"lat": 29.774, "lng": -90.025, "id": "156935", "name": "Pandora trilineata", "sprite": "sp-blue_mussel.png", "group": "clam_mussel", "rarity": 1}, {"lat": 29.7957, "lng": -90.4738, "id": "181580", "name": "Corbicula fluminea", "sprite": "sp-blue_mussel.png", "group": "clam_mussel", "rarity": 1}, {"lat": 31.4867, "lng": -90.1233, "id": "282217", "name": "Gulf logperch", "thumb": "tn_Pesut_u1.jpg", "sprite": "sp-dicentrarchus.png", "group": "bass", "rarity": 1, "waterType": "Brackish"}, {"lat": 30.95, "lng": -90.7945, "id": "1021987", "name": "Redfin pickerel", "thumb": "tn_Esame_u3.jpg", "sprite": "sp-anchoviella_juruasanga.png", "group": "other", "rarity": 1, "waterType": "Brackish"}, {"lat": 29.8014, "lng": -91.6514, "id": "210378", "name": "Penaeus monodon", "sprite": "sp-american_lobster.png", "group": "crab_lobster", "rarity": 1}, {"lat": 30.1025, "lng": -90.343, "id": "259670", "name": "Cassidinidea ovalis", "sprite": "sp-american_lobster.png", "group": "crab_lobster", "rarity": 1}, {"lat": 30.6764, "lng": -91.3908, "id": "505839", "name": "Corbula dietziana", "sprite": "sp-blue_mussel.png", "group": "clam_mussel", "rarity": 1}, {"lat": 29.8846, "lng": -90.3607, "id": "271955", "name": "Shrimp eel", "thumb": "tn_Opgom_u1.jpg", "sprite": "sp-electric_eel.png", "group": "eel", "rarity": 1, "waterType": "Saltwater"}, {"lat": 30.0506, "lng": -90.2707, "id": "159767", "name": "Naked goby", "thumb": "tn_Gobos_u2.jpg", "sprite": "sp-eviota_bipunctata.png", "group": "goby", "rarity": 1, "waterType": "Brackish"}, {"lat": 30.344, "lng": -90.233, "id": "146932", "name": "Paraonis fulgens", "sprite": "sp-anchoviella_juruasanga.png", "group": "other", "rarity": 1}, {"lat": 30.6764, "lng": -91.3908, "id": "397115", "name": "Stramonita floridana", "sprite": "sp-cowrie_shell.png", "group": "sea_snail", "rarity": 1}, {"lat": 30.2286, "lng": -90.2677, "id": "158829", "name": "Southern flounder", "thumb": "tn_Palet_u1.jpg", "sprite": "sp-atlantic_halibut.png", "group": "flatfish", "rarity": 1, "waterType": "Brackish"}, {"lat": 29.7356, "lng": -92.7372, "id": "138032", "name": "Gastrochaena", "sprite": "sp-blue_mussel.png", "group": "clam_mussel", "rarity": 1}, {"lat": 29.7231, "lng": -90.1236, "id": "272824", "name": "Band cusk-eel", "thumb": "tn_Ophol_u1.jpg", "sprite": "sp-anchoviella_juruasanga.png", "group": "other", "rarity": 1, "waterType": "Saltwater"}, {"lat": 29.7356, "lng": -92.7372, "id": "420358", "name": "Rubellatoma diomedea", "sprite": "sp-cowrie_shell.png", "group": "sea_snail", "rarity": 1}, {"lat": 30.1377, "lng": -91.0337, "id": "158823", "name": "Paralichthys", "sprite": "sp-atlantic_halibut.png", "group": "flatfish", "rarity": 1}, {"lat": 31.21, "lng": -92.57, "id": "1260621", "name": "Hydrobia milium", "sprite": "sp-cowrie_shell.png", "group": "sea_snail", "rarity": 1}, {"lat": 29.7356, "lng": -92.7372, "id": "420487", "name": "Turbonilla hemphilli", "sprite": "sp-cowrie_shell.png", "group": "sea_snail", "rarity": 1}, {"lat": 29.6, "lng": -91.4, "id": "157905", "name": "Probopyrus pandalicola", "sprite": "sp-american_lobster.png", "group": "crab_lobster", "rarity": 1}, {"lat": 30.4924, "lng": -90.8679, "id": "154198", "name": "Ameiurus", "sprite": "sp-blue_catfish.png", "group": "catfish", "rarity": 1}, {"lat": 30.7381, "lng": -91.4481, "id": "126737", "name": "Rainbow smelt", "thumb": "tn_Osmor_u1.jpg", "sprite": "sp-anchoviella_juruasanga.png", "group": "other", "rarity": 1, "waterType": "Brackish"}, {"lat": 31.0285, "lng": -91.5727, "id": "157872", "name": "Longnose gar", "thumb": "tn_Leoss_u5.jpg", "sprite": "sp-anchoviella_juruasanga.png", "group": "other", "rarity": 1, "waterType": "Brackish"}, {"lat": 30.7322, "lng": -90.877, "id": "151289", "name": "Lepomis", "sprite": "sp-dicentrarchus.png", "group": "bass", "rarity": 1}, {"lat": 30.6764, "lng": -91.3908, "id": "160174", "name": "Bittiolum varium", "sprite": "sp-cowrie_shell.png", "group": "sea_snail", "rarity": 1}, {"lat": 30.05, "lng": -90.177, "id": "136025", "name": "Phascolion", "sprite": "sp-anchoviella_juruasanga.png", "group": "other", "rarity": 1}, {"lat": 29.96, "lng": -91.279, "id": "160442", "name": "Sayella", "sprite": "sp-cowrie_shell.png", "group": "sea_snail", "rarity": 1}, {"lat": 29.7789, "lng": -90.1836, "id": "159576", "name": "Shortwing searobin", "thumb": "tn_Prste_u4.jpg", "sprite": "sp-anchoviella_juruasanga.png", "group": "other", "rarity": 1, "waterType": "Saltwater"}, {"lat": 30.6764, "lng": -91.3908, "id": "582802", "name": "Agriopoma texasianum", "sprite": "sp-blue_mussel.png", "group": "clam_mussel", "rarity": 1}, {"lat": 31.1702, "lng": -91.5008, "id": "159600", "name": "American gizzard shad", "thumb": "tn_Docep_u2.jpg", "sprite": "sp-anchoviella_juruasanga.png", "group": "other", "rarity": 1, "waterType": "Brackish"}, {"lat": 30.0752, "lng": -90.414, "id": "151158", "name": "Atlantic croaker", "thumb": "tn_Miund_u0.jpg", "sprite": "sp-anchoviella_juruasanga.png", "group": "other", "rarity": 1, "waterType": "Brackish"}, {"lat": 30.2333, "lng": -90.3333, "id": "276316", "name": "Featherduster blenny", "thumb": "tn_Hymul_u2.jpg", "sprite": "sp-helcogramma_ascensionis.png", "group": "blenny", "rarity": 1, "waterType": "Saltwater"}, {"lat": 30.3773, "lng": -90.1605, "id": "268224", "name": "Adinia", "sprite": "sp-anchoviella_juruasanga.png", "group": "other", "rarity": 1}, {"lat": 29.7356, "lng": -92.7372, "id": "156864", "name": "Martesia", "sprite": "sp-blue_mussel.png", "group": "clam_mussel", "rarity": 1}, {"lat": 30.6764, "lng": -91.3908, "id": "156070", "name": "Dosinia discus", "sprite": "sp-blue_mussel.png", "group": "clam_mussel", "rarity": 1}, {"lat": 30.3522, "lng": -90.7347, "id": "269387", "name": "Heterandria", "sprite": "sp-anchoviella_juruasanga.png", "group": "other", "rarity": 1}, {"lat": 30.0751, "lng": -90.1465, "id": "159166", "name": "Bay whiff", "thumb": "tn_Cispi_u1.jpg", "sprite": "sp-atlantic_halibut.png", "group": "flatfish", "rarity": 1, "waterType": "Brackish"}, {"lat": 30.4167, "lng": -91.025, "id": "342631", "name": "Crocodylidae", "sprite": "sp-anchoviella_juruasanga.png", "group": "other", "rarity": 1}, {"lat": 30.0828, "lng": -90.4027, "id": "157875", "name": "Ladyfish", "thumb": "tn_Elsau_u3.jpg", "sprite": "sp-anchoviella_juruasanga.png", "group": "other", "rarity": 1, "waterType": "Brackish"}, {"lat": 29.9934, "lng": -90.9518, "id": "129218", "name": "Mediomastus", "sprite": "sp-anchoviella_juruasanga.png", "group": "other", "rarity": 1}, {"lat": 30.328, "lng": -91.3908, "id": "456602", "name": "Lottia pelta", "sprite": "sp-cowrie_shell.png", "group": "sea_snail", "rarity": 1}, {"lat": 29.8569, "lng": -91.3513, "id": "157028", "name": "Lolliguncula brevis", "sprite": "sp-giant_pacific_octopus.png", "group": "octopus_squid", "rarity": 1}, {"lat": 29.7356, "lng": -92.7372, "id": "419836", "name": "Eulima bifasciata", "sprite": "sp-cowrie_shell.png", "group": "sea_snail", "rarity": 1}, {"lat": 29.8816, "lng": -91.2789, "id": "2039", "name": "Naididae", "sprite": "sp-anchoviella_juruasanga.png", "group": "other", "rarity": 1}, {"lat": 29.9538, "lng": -91.0267, "id": "105", "name": "Bivalvia", "sprite": "sp-blue_mussel.png", "group": "clam_mussel", "rarity": 1}, {"lat": 30.3143, "lng": -90.6093, "id": "126227", "name": "Syngnathus", "sprite": "sp-cosmocampus_coccineus.png", "group": "seahorse", "rarity": 1}, {"lat": 29.9735, "lng": -90.9378, "id": "878513", "name": "Ameritella mitchelli", "sprite": "sp-blue_mussel.png", "group": "clam_mussel", "rarity": 1}, {"lat": 29.7356, "lng": -92.7372, "id": "419997", "name": "Costoanachis similis", "sprite": "sp-cowrie_shell.png", "group": "sea_snail", "rarity": 1}, {"lat": 29.7583, "lng": -90.2343, "id": "101190", "name": "Laboea", "sprite": "sp-anchoviella_juruasanga.png", "group": "other", "rarity": 1}, {"lat": 30.6764, "lng": -91.3908, "id": "160063", "name": "Tectonatica pusilla", "sprite": "sp-cowrie_shell.png", "group": "sea_snail", "rarity": 1}, {"lat": 29.7517, "lng": -90.9502, "id": "275282", "name": "Least puffer", "thumb": "tn_Sppar_u0.jpg", "sprite": "sp-fahaka_pufferfish.png", "group": "pufferfish", "rarity": 1, "waterType": "Brackish"}, {"lat": 30.237, "lng": -90.288, "id": "558840", "name": "Prionospio perkinsi", "sprite": "sp-anchoviella_juruasanga.png", "group": "other", "rarity": 1}, {"lat": 30.053, "lng": -90.66, "id": "558283", "name": "Hermundura americana", "sprite": "sp-anchoviella_juruasanga.png", "group": "other", "rarity": 1}, {"lat": 29.7356, "lng": -92.7372, "id": "420808", "name": "Diplodonta punctata", "sprite": "sp-blue_mussel.png", "group": "clam_mussel", "rarity": 1}, {"lat": 30.065, "lng": -90.301, "id": "101679", "name": "Melita", "sprite": "sp-american_lobster.png", "group": "crab_lobster", "rarity": 1}, {"lat": 29.7356, "lng": -92.7372, "id": "140570", "name": "Smaragdia viridis", "sprite": "sp-cowrie_shell.png", "group": "sea_snail", "rarity": 1}, {"lat": 29.9304, "lng": -90.9648, "id": "127089", "name": "Largehead hairtail", "thumb": "tn_Trlep_u0.jpg", "sprite": "sp-anchoviella_juruasanga.png", "group": "other", "rarity": 1, "waterType": "Brackish"}, {"lat": 29.9035, "lng": -91.2774, "id": "131191", "name": "Streblospio benedicti", "sprite": "sp-anchoviella_juruasanga.png", "group": "other", "rarity": 1}, {"lat": 30.1667, "lng": -90.1617, "id": "158758", "name": "Inshore lizardfish", "thumb": "tn_Syfoe_u3.jpg", "sprite": "sp-anchoviella_juruasanga.png", "group": "other", "rarity": 1, "waterType": "Brackish"}, {"lat": 30.0189, "lng": -90.0641, "id": "159577", "name": "Bighead searobin", "thumb": "tn_Prtri_u1.jpg", "sprite": "sp-anchoviella_juruasanga.png", "group": "other", "rarity": 1, "waterType": "Saltwater"}, {"lat": 30.8003, "lng": -91.6151, "id": "154582", "name": "Common carp", "thumb": "tn_Cycar_ua.jpg", "sprite": "sp-enteromius.png", "group": "carp_minnow", "rarity": 1, "waterType": "Brackish"}, {"lat": 29.576, "lng": -91.624, "id": "157565", "name": "Scoloplos robustus", "sprite": "sp-anchoviella_juruasanga.png", "group": "other", "rarity": 1}, {"lat": 29.774, "lng": -90.025, "id": "1488282", "name": "Gomphus", "sprite": "sp-anchoviella_juruasanga.png", "group": "other", "rarity": 1}, {"lat": 29.8992, "lng": -91.0948, "id": "325821", "name": "Hermundura", "sprite": "sp-anchoviella_juruasanga.png", "group": "other", "rarity": 1}, {"lat": 29.9687, "lng": -90.9601, "id": "159304", "name": "Cynoscion", "sprite": "sp-anchoviella_juruasanga.png", "group": "other", "rarity": 1}, {"lat": 29.9152, "lng": -90.9767, "id": "505742", "name": "Mulinia pontchartrainensis", "sprite": "sp-blue_mussel.png", "group": "clam_mussel", "rarity": 1}, {"lat": 29.8659, "lng": -90.2526, "id": "276287", "name": "Mexican searobin", "thumb": "tn_Prpar_u1.jpg", "sprite": "sp-anchoviella_juruasanga.png", "group": "other", "rarity": 1, "waterType": "Brackish"}, {"lat": 30.1639, "lng": -90.1817, "id": "151802", "name": "Atlantic sturgeon", "thumb": "tn_Acoxy_u0.jpg", "sprite": "sp-atlantic_sturgeon.png", "group": "sturgeon", "rarity": 1, "waterType": "Brackish"}, {"lat": 29.7356, "lng": -92.7372, "id": "137820", "name": "Mangelia", "sprite": "sp-cowrie_shell.png", "group": "sea_snail", "rarity": 1}, {"lat": 30.183, "lng": -90.1, "id": "146493", "name": "Anilocra", "sprite": "sp-american_lobster.png", "group": "crab_lobster", "rarity": 1}, {"lat": 30.057, "lng": -90.0955, "id": "150868", "name": "Orthocladiinae", "sprite": "sp-anchoviella_juruasanga.png", "group": "other", "rarity": 1}, {"lat": 30.6764, "lng": -91.3908, "id": "420526", "name": "Haminoea succinea", "sprite": "sp-cowrie_shell.png", "group": "sea_snail", "rarity": 1}, {"lat": 30.0375, "lng": -90.3639, "id": "276077", "name": "Sand weakfish", "thumb": "tn_Cyare_u3.jpg", "sprite": "sp-anchoviella_juruasanga.png", "group": "other", "rarity": 1, "waterType": "Brackish"}, {"lat": 30.0, "lng": -90.05, "id": "101172", "name": "River lamprey", "thumb": "tn_Laflu_u0.jpg", "sprite": "sp-pacific_lamprey.png", "group": "lamprey", "rarity": 1, "waterType": "Brackish"}, {"lat": 29.75, "lng": -90.25, "id": "146950", "name": "Galathowenia oculata", "sprite": "sp-anchoviella_juruasanga.png", "group": "other", "rarity": 1}, {"lat": 30.1115, "lng": -90.1968, "id": "161345", "name": "Americamysis almyra", "sprite": "sp-american_lobster.png", "group": "crab_lobster", "rarity": 1}, {"lat": 29.8335, "lng": -92.6085, "id": "101537", "name": "Gammarus", "sprite": "sp-american_lobster.png", "group": "crab_lobster", "rarity": 1}, {"lat": 29.7356, "lng": -92.7372, "id": "404149", "name": "Eupleura sulcidentata", "sprite": "sp-cowrie_shell.png", "group": "sea_snail", "rarity": 1}, {"lat": 30.0514, "lng": -90.2498, "id": "158713", "name": "Gafftopsail sea catfish", "thumb": "tn_Bamar_u7.jpg", "sprite": "sp-blue_catfish.png", "group": "catfish", "rarity": 1, "waterType": "Brackish"}, {"lat": 29.928, "lng": -91.168, "id": "886228", "name": "Tanypus", "sprite": "sp-anchoviella_juruasanga.png", "group": "other", "rarity": 1}, {"lat": 30.9647, "lng": -91.7055, "id": "594789", "name": "Black carp", "thumb": "tn_Mypic_u1.jpg", "sprite": "sp-enteromius.png", "group": "carp_minnow", "rarity": 1, "waterType": "Brackish"}, {"lat": 29.7081, "lng": -91.5937, "id": "159810", "name": "Longspine porgy", "thumb": "tn_Stcap_u0.jpg", "sprite": "sp-anchoviella_juruasanga.png", "group": "other", "rarity": 1, "waterType": "Saltwater"}, {"lat": 31.21, "lng": -92.57, "id": "1420158", "name": "Hydrobia dalli", "sprite": "sp-cowrie_shell.png", "group": "sea_snail", "rarity": 1}, {"lat": 30.3576, "lng": -90.7217, "id": "159256", "name": "Atlantic needlefish", "thumb": "tn_Stmar_u5.jpg", "sprite": "sp-anchoviella_juruasanga.png", "group": "other", "rarity": 1, "waterType": "Brackish"}]}