{"zoom": 7, "x": 3, "y": 24, "points": [{"lat": 73.7517, "lng": -170.9, "id": "103251", "name": "Hyperia galba", "sprite": "sp-american_lobster.png", "group": "crab_lobster", "rarity": 1}, {"lat": 73.6271, "lng": -170.5626, "id": "117265", "name": "Aeginopsis laurentii", "sprite": "sp-anchoviella_juruasanga.png", "group": "other", "rarity": 1}, {"lat": 73.7517, "lng": -170.9, "id": "139178", "name": "Clione limacina", "sprite": "sp-cowrie_shell.png", "group": "sea_snail", "rarity": 1}, {"lat": 73.3006, "lng": -168.7956, "id": "1205", "name": "Hyperiidea", "sprite": "sp-american_lobster.png", "group": "crab_lobster", "rarity": 1}, {"lat": 73.7517, "lng": -170.9, "id": "135418", "name": "Dimophyes arctica", "sprite": "sp-anchoviella_juruasanga.png", "group": "other", "rarity": 1}, {"lat": 73.6772, "lng": -170.9889, "id": "104513", "name": "Microcalanus pygmaeus", "sprite": "sp-anchoviella_juruasanga.png", "group": "other", "rarity": 1}, {"lat": 73.5567, "lng": -170.2519, "id": "1080", "name": "Copepoda", "sprite": "sp-anchoviella_juruasanga.png", "group": "other", "rarity": 1}, {"lat": 73.559, "lng": -170.3749, "id": "1337", "name": "Hydrozoa", "sprite": "sp-anchoviella_juruasanga.png", "group": "other", "rarity": 1}, {"lat": 73.7517, "lng": -170.9, "id": "346037", "name": "Acartia (Acartiura) longiremis", "sprite": "sp-anchoviella_juruasanga.png", "group": "other", "rarity": 1}, {"lat": 73.7517, "lng": -170.9, "id": "112197", "name": "Globigerina", "sprite": "sp-anchoviella_juruasanga.png", "group": "other", "rarity": 1}, {"lat": 73.7517, "lng": -170.9, "id": "140223", "name": "Limacina helicina", "sprite": "sp-cowrie_shell.png", "group": "sea_snail", "rarity": 1}, {"lat": 73.6772, "lng": -170.9889, "id": "104517", "name": "Pseudocalanus minutus", "sprite": "sp-anchoviella_juruasanga.png", "group": "other", "rarity": 1}, {"lat": 73.5283, "lng": -171.1667, "id": "196874", "name": "Paraeuchaeta", "sprite": "sp-anchoviella_juruasanga.png", "group": "other", "rarity": 1}, {"lat": 73.3006, "lng": -168.7956, "id": "106673", "name": "Brachyura", "sprite": "sp-american_lobster.png", "group": "crab_lobster", "rarity": 1}, {"lat": 73.7517, "lng": -170.9, "id": "1102", "name": "Harpacticoida", "sprite": "sp-anchoviella_juruasanga.png", "group": "other", "rarity": 1}, {"lat": 73.3006, "lng": -168.7956, "id": "1128", "name": "Euphausiacea", "sprite": "sp-antarctic_krill.png", "group": "shrimp", "rarity": 1}, {"lat": 74.0167, "lng": -168.8333, "id": "2", "name": "Animalia", "sprite": "sp-anchoviella_juruasanga.png", "group": "other", "rarity": 1}, {"lat": 73.3006, "lng": -168.7956, "id": "103354", "name": "Fritillariidae", "sprite": "sp-anchoviella_juruasanga.png", "group": "other", "rarity": 1}, {"lat": 73.5841, "lng": -171.1, "id": "883", "name": "Polychaeta", "sprite": "sp-anchoviella_juruasanga.png", "group": "other", "rarity": 1}, {"lat": 73.3006, "lng": -168.7956, "id": "104085", "name": "Eucalanidae", "sprite": "sp-anchoviella_juruasanga.png", "group": "other", "rarity": 1}, {"lat": 73.3006, "lng": -168.7956, "id": "146421", "name": "Appendicularia", "sprite": "sp-anchoviella_juruasanga.png", "group": "other", "rarity": 1}, {"lat": 73.3006, "lng": -168.7956, "id": "2081", "name": "Chaetognatha", "sprite": "sp-anchoviella_juruasanga.png", "group": "other", "rarity": 1}, {"lat": 73.3006, "lng": -168.7956, "id": "109444", "name": "Pyrocystaceae", "sprite": "sp-anchoviella_juruasanga.png", "group": "other", "rarity": 1}, {"lat": 73.6959, "lng": -170.9667, "id": "104152", "name": "Calanus", "sprite": "sp-anchoviella_juruasanga.png", "group": "other", "rarity": 1}, {"lat": 73.3006, "lng": -168.7956, "id": "104308", "name": "Gaetanus curvicornis", "sprite": "sp-anchoviella_juruasanga.png", "group": "other", "rarity": 1}, {"lat": 73.7055, "lng": -170.9552, "id": "104467", "name": "Calanus hyperboreus", "sprite": "sp-anchoviella_juruasanga.png", "group": "other", "rarity": 1}, {"lat": 73.3006, "lng": -168.7956, "id": "1248", "name": "Ctenophora", "sprite": "sp-anchoviella_juruasanga.png", "group": "other", "rarity": 1}, {"lat": 73.3006, "lng": -168.7956, "id": "582419", "name": "Harosa", "sprite": "sp-anchoviella_juruasanga.png", "group": "other", "rarity": 1}, {"lat": 73.7517, "lng": -170.9, "id": "104470", "name": "Neocalanus cristatus", "sprite": "sp-anchoviella_juruasanga.png", "group": "other", "rarity": 1}, {"lat": 73.3006, "lng": -168.7956, "id": "104081", "name": "Centropagidae", "sprite": "sp-anchoviella_juruasanga.png", "group": "other", "rarity": 1}, {"lat": 73.3006, "lng": -168.7956, "id": "104165", "name": "Pseudocalanus", "sprite": "sp-anchoviella_juruasanga.png", "group": "other", "rarity": 1}, {"lat": 73.3006, "lng": -168.7956, "id": "1066", "name": "Crustacea", "sprite": "sp-anchoviella_juruasanga.png", "group": "other", "rarity": 1}, {"lat": 73.7517, "lng": -170.9, "id": "582421", "name": "Radiozoa", "sprite": "sp-anchoviella_juruasanga.png", "group": "other", "rarity": 1}, {"lat": 73.3006, "lng": -168.7956, "id": "1267", "name": "Cnidaria", "sprite": "sp-anchoviella_juruasanga.png", "group": "other", "rarity": 1}, {"lat": 73.3006, "lng": -168.7956, "id": "101383", "name": "Gammaridae", "sprite": "sp-american_lobster.png", "group": "crab_lobster", "rarity": 1}, {"lat": 73.3006, "lng": -168.7956, "id": "104086", "name": "Euchaetidae", "sprite": "sp-anchoviella_juruasanga.png", "group": "other", "rarity": 1}, {"lat": 73.3006, "lng": -168.7956, "id": "1100", "name": "Calanoida", "sprite": "sp-anchoviella_juruasanga.png", "group": "other", "rarity": 1}, {"lat": 73.3006, "lng": -168.7956, "id": "104074", "name": "Acartiidae", "sprite": "sp-anchoviella_juruasanga.png", "group": "other", "rarity": 1}, {"lat": 73.5283, "lng": -171.1667, "id": "834720", "name": "Halitholus yoldiaearcticae", "sprite": "sp-anchoviella_juruasanga.png", "group": "other", "rarity": 1}, {"lat": 73.64, "lng": -171.0333, "id": "110711", "name": "Thysanoessa raschii", "sprite": "sp-antarctic_krill.png", "group": "shrimp", "rarity": 1}, {"lat": 73.3006, "lng": -168.7956, "id": "1371", "name": "Siphonophorae", "sprite": "sp-anchoviella_juruasanga.png", "group": "other", "rarity": 1}, {"lat": 73.3006, "lng": -168.7956, "id": "103356", "name": "Oikopleuridae", "sprite": "sp-anchoviella_juruasanga.png", "group": "other", "rarity": 1}, {"lat": 73.7, "lng": -169.017, "id": "117790", "name": "Leuckartiara nobilis", "sprite": "sp-anchoviella_juruasanga.png", "group": "other", "rarity": 1}, {"lat": 73.5283, "lng": -171.1667, "id": "117562", "name": "Euphysa flammea", "sprite": "sp-anchoviella_juruasanga.png", "group": "other", "rarity": 1}, {"lat": 73.3006, "lng": -168.7956, "id": "106422", "name": "Oithonidae", "sprite": "sp-anchoviella_juruasanga.png", "group": "other", "rarity": 1}, {"lat": 73.451, "lng": -169.497, "id": "1078", "name": "Ostracoda", "sprite": "sp-anchoviella_juruasanga.png", "group": "other", "rarity": 1}, {"lat": 73.3833, "lng": -168.905, "id": "137085", "name": "Ursus maritimus", "sprite": "sp-anchoviella_juruasanga.png", "group": "other", "rarity": 1}, {"lat": 73.3006, "lng": -168.7956, "id": "135338", "name": "Diphyidae", "sprite": "sp-anchoviella_juruasanga.png", "group": "other", "rarity": 1}, {"lat": 74.001, "lng": -169.993, "id": "6", "name": "Bacteria", "sprite": "sp-anchoviella_juruasanga.png", "group": "other", "rarity": 1}, {"lat": 73.6772, "lng": -170.9889, "id": "103375", "name": "Fritillaria borealis", "sprite": "sp-anchoviella_juruasanga.png", "group": "other", "rarity": 1}, {"lat": 73.7314, "lng": -170.9242, "id": "104632", "name": "Metridia longa", "sprite": "sp-anchoviella_juruasanga.png", "group": "other", "rarity": 1}, {"lat": 73.3006, "lng": -168.7956, "id": "117213", "name": "Aglaura", "sprite": "sp-anchoviella_juruasanga.png", "group": "other", "rarity": 1}, {"lat": 73.3006, "lng": -168.7956, "id": "104079", "name": "Calanidae", "sprite": "sp-anchoviella_juruasanga.png", "group": "other", "rarity": 1}, {"lat": 73.3006, "lng": -168.7956, "id": "882", "name": "Annelida", "sprite": "sp-anchoviella_juruasanga.png", "group": "other", "rarity": 1}, {"lat": 73.53, "lng": -171.167, "id": "127111", "name": "Canadian eelpout", "thumb": "tn_Lypol_u0.jpg", "sprite": "sp-anchoviella_juruasanga.png", "group": "other", "rarity": 1, "waterType": "Saltwater"}, {"lat": 73.76, "lng": -170.95, "id": "126433", "name": "Polar cod", "thumb": "tn_Bosai_u0.jpg", "sprite": "sp-arctogadus.png", "group": "cod", "rarity": 1, "waterType": "Brackish"}, {"lat": 73.3006, "lng": -168.7956, "id": "128586", "name": "Oncaeidae", "sprite": "sp-anchoviella_juruasanga.png", "group": "other", "rarity": 1}, {"lat": 73.3006, "lng": -168.7956, "id": "51", "name": "Mollusca", "sprite": "sp-anchoviella_juruasanga.png", "group": "other", "rarity": 1}, {"lat": 73.8054, "lng": -169.9538, "id": "117849", "name": "Aglantha digitale", "sprite": "sp-anchoviella_juruasanga.png", "group": "other", "rarity": 1}, {"lat": 73.7517, "lng": -170.9, "id": "128956", "name": "Triconia borealis", "sprite": "sp-anchoviella_juruasanga.png", "group": "other", "rarity": 1}, {"lat": 73.6959, "lng": -170.9667, "id": "105440", "name": "Parasagitta elegans", "sprite": "sp-anchoviella_juruasanga.png", "group": "other", "rarity": 1}, {"lat": 73.6658, "lng": -171.0026, "id": "106656", "name": "Oithona similis", "sprite": "sp-anchoviella_juruasanga.png", "group": "other", "rarity": 1}, {"lat": 73.7128, "lng": -170.9464, "id": "104464", "name": "Calanus finmarchicus", "sprite": "sp-anchoviella_juruasanga.png", "group": "other", "rarity": 1}, {"lat": 73.3006, "lng": -168.7956, "id": "135220", "name": "Scyphozoa", "sprite": "sp-box_jellyfish.png", "group": "jellyfish", "rarity": 1}, {"lat": 73.3006, "lng": -168.7956, "id": "13704", "name": "Limacinidae", "sprite": "sp-cowrie_shell.png", "group": "sea_snail", "rarity": 1}, {"lat": 73.707, "lng": -170.9533, "id": "101", "name": "Gastropoda", "sprite": "sp-cowrie_shell.png", "group": "sea_snail", "rarity": 1}, {"lat": 73.3006, "lng": -168.7956, "id": "128569", "name": "Corycaeidae", "sprite": "sp-anchoviella_juruasanga.png", "group": "other", "rarity": 1}, {"lat": 73.7517, "lng": -170.9, "id": "1806", "name": "Echinodermata", "sprite": "sp-sea_cucumber.png", "group": "starfish", "rarity": 1}, {"lat": 73.6013, "lng": -170.1985, "id": "104075", "name": "Aetideidae", "sprite": "sp-anchoviella_juruasanga.png", "group": "other", "rarity": 1}, {"lat": 73.683, "lng": -170.9821, "id": "103413", "name": "Oikopleura (Vexillaria) labradoriensis", "sprite": "sp-anchoviella_juruasanga.png", "group": "other", "rarity": 1}, {"lat": 73.3006, "lng": -168.7956, "id": "104092", "name": "Metridinidae", "sprite": "sp-anchoviella_juruasanga.png", "group": "other", "rarity": 1}, {"lat": 73.3006, "lng": -168.7956, "id": "1082", "name": "Cirripedia", "sprite": "sp-anchoviella_juruasanga.png", "group": "other", "rarity": 1}, {"lat": 73.7517, "lng": -170.9, "id": "1509944", "name": "Scolecithricella minor minor", "sprite": "sp-anchoviella_juruasanga.png", "group": "other", "rarity": 1}]}