{"zoom": 7, "x": 71, "y": 75, "points": [{"lat": -29.9991, "lng": 21.4645, "id": "212583", "name": "Diomedea exulans", "sprite": "sp-anchoviella_juruasanga.png", "group": "other", "rarity": 1}, {"lat": -31.4242, "lng": 21.7575, "id": "1468428", "name": "Chubbyhead barb", "thumb": "tn_Baano_u0.jpg", "sprite": "sp-enteromius.png", "group": "carp_minnow", "rarity": 1, "waterType": "Brackish"}, {"lat": -31.8906, "lng": 19.7977, "id": "212651", "name": "Procellaria aequinoctialis", "sprite": "sp-anchoviella_juruasanga.png", "group": "other", "rarity": 1}, {"lat": -31.7667, "lng": 19.7, "id": "137189", "name": "Hydrobates pelagicus", "sprite": "sp-anchoviella_juruasanga.png", "group": "other", "rarity": 1}, {"lat": -31.6583, "lng": 21.5667, "id": "154582", "name": "Common carp", "thumb": "tn_Cycar_ua.jpg", "sprite": "sp-enteromius.png", "group": "carp_minnow", "rarity": 1, "waterType": "Brackish"}, {"lat": -31.83, "lng": 22.13, "id": "137135", "name": "Chlidonias hybrida", "sprite": "sp-anchoviella_juruasanga.png", "group": "other", "rarity": 1}, {"lat": -30.7933, "lng": 20.7523, "id": "137165", "name": "Sterna paradisaea", "sprite": "sp-anchoviella_juruasanga.png", "group": "other", "rarity": 1}, {"lat": -29.7592, "lng": 21.3721, "id": "343995", "name": "Thalassarche melanophris", "sprite": "sp-anchoviella_juruasanga.png", "group": "other", "rarity": 1}]}