{"zoom": 7, "x": 109, "y": 43, "points": [{"lat": 50.27, "lng": 127.4758, "id": "474063", "name": "Amurosaurus riabinini", "era": "Cretaceous", "type": "Ornithischian", "early_age": 72.2, "late_age": 66.0, "country": "RU"}, {"lat": 50.27, "lng": 127.4758, "id": "474064", "name": "Tyrannosauridae", "era": "Cretaceous", "type": "Theropod", "early_age": 72.2, "late_age": 66.0, "country": "RU"}, {"lat": 50.27, "lng": 127.4758, "id": "474146", "name": "Kerberosaurus manakini", "era": "Cretaceous", "type": "Ornithischian", "early_age": 72.2, "late_age": 66.0, "country": "RU"}, {"lat": 50.27, "lng": 127.4758, "id": "474149", "name": "Nodosauridae", "era": "Cretaceous", "type": "Ornithischian", "early_age": 72.2, "late_age": 66.0, "country": "RU"}, {"lat": 50.27, "lng": 127.4758, "id": "651206", "name": "Troodon", "era": "Cretaceous", "type": "Theropod", "early_age": 72.2, "late_age": 66.0, "country": "RU"}, {"lat": 50.27, "lng": 127.4758, "id": "1439149", "name": "Dromaeosaurinae", "era": "Cretaceous", "type": "Theropod", "early_age": 72.2, "late_age": 66.0, "country": "RU"}, {"lat": 50.27, "lng": 127.4758, "id": "1566586", "name": "Velociraptorinae", "era": "Cretaceous", "type": "Theropod", "early_age": 72.2, "late_age": 66.0, "country": "RU"}]}