{"zoom": 7, "x": 72, "y": 48, "points": [{"lat": 40.3747, "lng": 23.1667, "id": "1350594", "name": "Alectoris graeca", "era": "Cretaceous", "type": "Theropod", "early_age": 2.6, "late_age": 0.0, "country": "GR"}, {"lat": 40.3747, "lng": 23.1667, "id": "1350595", "name": "Alectoris", "era": "Cretaceous", "type": "Theropod", "early_age": 2.6, "late_age": 0.0, "country": "GR"}, {"lat": 38.9211, "lng": 23.3172, "id": "1414976", "name": "Pavo archiaci", "era": "Cretaceous", "type": "Theropod", "early_age": 11.6, "late_age": 5.3, "country": "GR"}]}